GoblinStockAlerts/__init__.py
GoblinStockAlerts/__version__.py
GoblinStockAlerts-10.dist-info/METADATA
GoblinStockAlerts-10.dist-info/WHEEL
GoblinStockAlerts-10.dist-info/top_level.txt
GoblinStockAlerts-10.dist-info/RECORD
