Metadata-Version: 2.1
Name: GoblinStockAlerts
Version: 10
Summary: GoblinStockAlerts has been discontinued.
Author: binaryhabitat
License: UNKNOWN
Platform: UNKNOWN
Requires-Python: >=3.6
